plugin_foundation/__init__.py
plugin_foundation/data.py
plugin_foundation/jinja2_env.py
one_cli_plugin_foundation-0.0.2.dist-info/LICENSE
one_cli_plugin_foundation-0.0.2.dist-info/METADATA
one_cli_plugin_foundation-0.0.2.dist-info/WHEEL
one_cli_plugin_foundation-0.0.2.dist-info/top_level.txt
one_cli_plugin_foundation-0.0.2.dist-info/RECORD
