Metadata-Version: 2.1
Name: one-cli-plugin-foundation
Version: 0.0.2
Summary: This is a one-cli plugin to help create new DNX foundations.
Home-page: https://github.com/DNXLabs/plugin-foundation
Author: DNX Solutions
Author-email: contact@dnx.solutions
License: Apache License 2.0
Platform: UNKNOWN
Classifier: Development Status :: 5 - Production/Stable
Classifier: Intended Audience :: Developers
Classifier: Intended Audience :: System Administrators
Classifier: Natural Language :: English
Classifier: License :: OSI Approved :: Apache Software License
Classifier: Programming Language :: Python
Classifier: Programming Language :: Python :: 3
Classifier: Programming Language :: Python :: 3.4
Classifier: Programming Language :: Python :: 3.5
Classifier: Programming Language :: Python :: 3.6
Classifier: Programming Language :: Python :: 3.7
Classifier: Programming Language :: Python :: 3.8
Requires-Python: >=3.6
Requires-Dist: gitpython (==3.1.12)
Requires-Dist: jinja2 (==2.11.3)
Requires-Dist: jinja2-ansible-filters (==1.3.0)
